{
  "name": "Tempoross",
  "slug": "tempoross",
  "table_id": 67,
  "hiscores_url": "https://secure.runescape.com/m=hiscore_oldschool/overall?category_type=1&table=67",
  "wiki_page": "Reward pool",
  "wiki_url": "https://oldschool.runescape.wiki/w/Reward_pool",
  "wiki_sections": [
    "Rewards"
  ],
  "activity_image_path": "assets/activities/tempoross.png",
  "supported": true,
  "note": null,
  "simulation_disabled": false,
  "leaderboard_path": "data/leaderboards/tempoross.json",
  "leaderboard_preview": [
    {
      "rank": 1,
      "name": "Uncle Solo",
      "score": 28804
    },
    {
      "rank": 2,
      "name": "Kait",
      "score": 23602
    },
    {
      "rank": 3,
      "name": "Kaguya",
      "score": 22200
    },
    {
      "rank": 4,
      "name": "Tribuo",
      "score": 17500
    },
    {
      "rank": 5,
      "name": "iNewton",
      "score": 15286
    },
    {
      "rank": 6,
      "name": "SteffRS",
      "score": 14500
    },
    {
      "rank": 7,
      "name": "Fish4Lily",
      "score": 13795
    },
    {
      "rank": 8,
      "name": "ChimeraCore",
      "score": 11111
    },
    {
      "rank": 9,
      "name": "Zaxynn G",
      "score": 10782
    },
    {
      "rank": 10,
      "name": "Skipper996",
      "score": 10468
    }
  ],
  "drop_rows": [
    {
      "item_name": "Spirit flakes",
      "item_slug": "spirit-flakes",
      "item_page": "https://oldschool.runescape.wiki/w/Spirit_flakes",
      "item_asset_path": "assets/items/spirit-flakes.png",
      "section": "Unique",
      "quantity_text": "32\u201364",
      "quantity_estimate": 48.0,
      "rarity_fraction": "1/4",
      "rarity_percent": "25",
      "probability": 0.25,
      "ge_value": null,
      "ge_unit_estimate": null,
      "ha_value": 32,
      "ha_unit_estimate": 1,
      "row_id": "Unique::spirit-flakes::1/4"
    },
    {
      "item_name": "Casket (Reward pool)",
      "item_slug": "casket-reward-pool",
      "item_page": "https://oldschool.runescape.wiki/w/Casket_(Reward_pool)",
      "item_asset_path": "assets/items/casket-reward-pool.png",
      "section": "Unique",
      "quantity_text": "1",
      "quantity_estimate": 1.0,
      "rarity_fraction": "1/20",
      "rarity_percent": "5",
      "probability": 0.05,
      "ge_value": null,
      "ge_unit_estimate": null,
      "ha_value": null,
      "ha_unit_estimate": null,
      "row_id": "Unique::casket-reward-pool::1/20"
    },
    {
      "item_name": "Soaked page",
      "item_slug": "soaked-page",
      "item_page": "https://oldschool.runescape.wiki/w/Soaked_page",
      "item_asset_path": "assets/items/soaked-page.png",
      "section": "Unique",
      "quantity_text": "5\u20139",
      "quantity_estimate": 7.0,
      "rarity_fraction": "149/8,000",
      "rarity_percent": "1.86",
      "probability": 0.018625,
      "ge_value": 14495,
      "ge_unit_estimate": 2071,
      "ha_value": 510,
      "ha_unit_estimate": 73,
      "row_id": "Unique::soaked-page::149/8,000"
    },
    {
      "item_name": "Fish barrel",
      "item_slug": "fish-barrel",
      "item_page": "https://oldschool.runescape.wiki/w/Fish_barrel",
      "item_asset_path": "assets/items/fish-barrel.png",
      "section": "Unique",
      "quantity_text": "1",
      "quantity_estimate": 1.0,
      "rarity_fraction": "1/400",
      "rarity_percent": "0.25",
      "probability": 0.0025,
      "ge_value": null,
      "ge_unit_estimate": null,
      "ha_value": null,
      "ha_unit_estimate": null,
      "row_id": "Unique::fish-barrel::1/400"
    },
    {
      "item_name": "Soaked page",
      "item_slug": "soaked-page",
      "item_page": "https://oldschool.runescape.wiki/w/Soaked_page",
      "item_asset_path": "assets/items/soaked-page.png",
      "section": "Unique",
      "quantity_text": "25",
      "quantity_estimate": 25.0,
      "rarity_fraction": "1/400",
      "rarity_percent": "0.25",
      "probability": 0.0025,
      "ge_value": 72475,
      "ge_unit_estimate": 2899,
      "ha_value": 2550,
      "ha_unit_estimate": 102,
      "row_id": "Unique::soaked-page::1/400"
    },
    {
      "item_name": "Tackle box",
      "item_slug": "tackle-box",
      "item_page": "https://oldschool.runescape.wiki/w/Tackle_box",
      "item_asset_path": "assets/items/tackle-box.png",
      "section": "Unique",
      "quantity_text": "1",
      "quantity_estimate": 1.0,
      "rarity_fraction": "1/400",
      "rarity_percent": "0.25",
      "probability": 0.0025,
      "ge_value": null,
      "ge_unit_estimate": null,
      "ha_value": null,
      "ha_unit_estimate": null,
      "row_id": "Unique::tackle-box::1/400"
    },
    {
      "item_name": "Big harpoonfish",
      "item_slug": "big-harpoonfish",
      "item_page": "https://oldschool.runescape.wiki/w/Big_harpoonfish",
      "item_asset_path": "assets/items/big-harpoonfish.png",
      "section": "Unique",
      "quantity_text": "1",
      "quantity_estimate": 1.0,
      "rarity_fraction": "1/1,600",
      "rarity_percent": "0.0625",
      "probability": 0.000625,
      "ge_value": null,
      "ge_unit_estimate": null,
      "ha_value": 2100,
      "ha_unit_estimate": 2100,
      "row_id": "Unique::big-harpoonfish::1/1,600"
    },
    {
      "item_name": "Tome of water (empty)",
      "item_slug": "tome-of-water-empty",
      "item_page": "https://oldschool.runescape.wiki/w/Tome_of_water_(empty)",
      "item_asset_path": "assets/items/tome-of-water-empty.png",
      "section": "Unique",
      "quantity_text": "1",
      "quantity_estimate": 1.0,
      "rarity_fraction": "1/1,600",
      "rarity_percent": "0.0625",
      "probability": 0.000625,
      "ge_value": 463658,
      "ge_unit_estimate": 463658,
      "ha_value": 11700,
      "ha_unit_estimate": 11700,
      "row_id": "Unique::tome-of-water-empty::1/1,600"
    },
    {
      "item_name": "Tiny tempor",
      "item_slug": "tiny-tempor",
      "item_page": "https://oldschool.runescape.wiki/w/Tiny_tempor",
      "item_asset_path": "assets/items/tiny-tempor.png",
      "section": "Unique",
      "quantity_text": "1",
      "quantity_estimate": 1.0,
      "rarity_fraction": "1/8,000",
      "rarity_percent": "0.0125",
      "probability": 0.000125,
      "ge_value": null,
      "ge_unit_estimate": null,
      "ha_value": null,
      "ha_unit_estimate": null,
      "row_id": "Unique::tiny-tempor::1/8,000"
    },
    {
      "item_name": "Dragon harpoon",
      "item_slug": "dragon-harpoon",
      "item_page": "https://oldschool.runescape.wiki/w/Dragon_harpoon",
      "item_asset_path": "assets/items/dragon-harpoon.png",
      "section": "Unique",
      "quantity_text": "1",
      "quantity_estimate": 1.0,
      "rarity_fraction": "1/8,000",
      "rarity_percent": "0.0125",
      "probability": 0.000125,
      "ge_value": 2901582,
      "ge_unit_estimate": 2901582,
      "ha_value": 33000,
      "ha_unit_estimate": 33000,
      "row_id": "Unique::dragon-harpoon::1/8,000"
    },
    {
      "item_name": "Raw herring",
      "item_slug": "raw-herring",
      "item_page": "https://oldschool.runescape.wiki/w/Raw_herring",
      "item_asset_path": "assets/items/raw-herring.png",
      "section": "Levels 35\u201339",
      "quantity_text": "30\u201340 (noted)",
      "quantity_estimate": 35.0,
      "rarity_fraction": "900/6,400",
      "rarity_percent": "14.1",
      "probability": 0.140625,
      "ge_value": 1650,
      "ge_unit_estimate": 47,
      "ha_value": 180,
      "ha_unit_estimate": 5,
      "row_id": "Levels 35\u201339::raw-herring::900/6,400"
    },
    {
      "item_name": "Raw mackerel",
      "item_slug": "raw-mackerel",
      "item_page": "https://oldschool.runescape.wiki/w/Raw_mackerel",
      "item_asset_path": "assets/items/raw-mackerel.png",
      "section": "Levels 35\u201339",
      "quantity_text": "20\u201330 (noted)",
      "quantity_estimate": 25.0,
      "rarity_fraction": "810/6,400",
      "rarity_percent": "12.7",
      "probability": 0.1265625,
      "ge_value": 420,
      "ge_unit_estimate": 17,
      "ha_value": 180,
      "ha_unit_estimate": 7,
      "row_id": "Levels 35\u201339::raw-mackerel::810/6,400"
    },
    {
      "item_name": "Raw pike",
      "item_slug": "raw-pike",
      "item_page": "https://oldschool.runescape.wiki/w/Raw_pike",
      "item_asset_path": "assets/items/raw-pike.png",
      "section": "Levels 35\u201339",
      "quantity_text": "10\u201320 (noted)",
      "quantity_estimate": 15.0,
      "rarity_fraction": "720/6,400",
      "rarity_percent": "11.3",
      "probability": 0.1125,
      "ge_value": 1570,
      "ge_unit_estimate": 105,
      "ha_value": 120,
      "ha_unit_estimate": 8,
      "row_id": "Levels 35\u201339::raw-pike::720/6,400"
    },
    {
      "item_name": "Raw salmon",
      "item_slug": "raw-salmon",
      "item_page": "https://oldschool.runescape.wiki/w/Raw_salmon",
      "item_asset_path": "assets/items/raw-salmon.png",
      "section": "Levels 35\u201339",
      "quantity_text": "7\u201312 (noted)",
      "quantity_estimate": 9.5,
      "rarity_fraction": "630/6,400",
      "rarity_percent": "9.84",
      "probability": 0.0984375,
      "ge_value": 315,
      "ge_unit_estimate": 33,
      "ha_value": 126,
      "ha_unit_estimate": 13,
      "row_id": "Levels 35\u201339::raw-salmon::630/6,400"
    },
    {
      "item_name": "Raw tuna",
      "item_slug": "raw-tuna",
      "item_page": "https://oldschool.runescape.wiki/w/Raw_tuna",
      "item_asset_path": "assets/items/raw-tuna.png",
      "section": "Levels 35\u201339",
      "quantity_text": "5\u201310 (noted)",
      "quantity_estimate": 7.5,
      "rarity_fraction": "540/6,400",
      "rarity_percent": "8.44",
      "probability": 0.084375,
      "ge_value": 330,
      "ge_unit_estimate": 44,
      "ha_value": 120,
      "ha_unit_estimate": 16,
      "row_id": "Levels 35\u201339::raw-tuna::540/6,400"
    },
    {
      "item_name": "Raw mackerel",
      "item_slug": "raw-mackerel",
      "item_page": "https://oldschool.runescape.wiki/w/Raw_mackerel",
      "item_asset_path": "assets/items/raw-mackerel.png",
      "section": "Levels 40\u201345",
      "quantity_text": "30\u201340 (noted)",
      "quantity_estimate": 35.0,
      "rarity_fraction": "900/6,400",
      "rarity_percent": "14.1",
      "probability": 0.140625,
      "ge_value": 630,
      "ge_unit_estimate": 18,
      "ha_value": 270,
      "ha_unit_estimate": 8,
      "row_id": "Levels 40\u201345::raw-mackerel::900/6,400"
    },
    {
      "item_name": "Raw pike",
      "item_slug": "raw-pike",
      "item_page": "https://oldschool.runescape.wiki/w/Raw_pike",
      "item_asset_path": "assets/items/raw-pike.png",
      "section": "Levels 40\u201345",
      "quantity_text": "20\u201330 (noted)",
      "quantity_estimate": 25.0,
      "rarity_fraction": "810/6,400",
      "rarity_percent": "12.7",
      "probability": 0.1265625,
      "ge_value": 3140,
      "ge_unit_estimate": 126,
      "ha_value": 240,
      "ha_unit_estimate": 10,
      "row_id": "Levels 40\u201345::raw-pike::810/6,400"
    },
    {
      "item_name": "Raw salmon",
      "item_slug": "raw-salmon",
      "item_page": "https://oldschool.runescape.wiki/w/Raw_salmon",
      "item_asset_path": "assets/items/raw-salmon.png",
      "section": "Levels 40\u201345",
      "quantity_text": "10\u201320 (noted)",
      "quantity_estimate": 15.0,
      "rarity_fraction": "720/6,400",
      "rarity_percent": "11.3",
      "probability": 0.1125,
      "ge_value": 450,
      "ge_unit_estimate": 30,
      "ha_value": 180,
      "ha_unit_estimate": 12,
      "row_id": "Levels 40\u201345::raw-salmon::720/6,400"
    },
    {
      "item_name": "Raw tuna",
      "item_slug": "raw-tuna",
      "item_page": "https://oldschool.runescape.wiki/w/Raw_tuna",
      "item_asset_path": "assets/items/raw-tuna.png",
      "section": "Levels 40\u201345",
      "quantity_text": "7\u201312 (noted)",
      "quantity_estimate": 9.5,
      "rarity_fraction": "630/6,400",
      "rarity_percent": "9.84",
      "probability": 0.0984375,
      "ge_value": 462,
      "ge_unit_estimate": 49,
      "ha_value": 168,
      "ha_unit_estimate": 18,
      "row_id": "Levels 40\u201345::raw-tuna::630/6,400"
    },
    {
      "item_name": "Raw lobster",
      "item_slug": "raw-lobster",
      "item_page": "https://oldschool.runescape.wiki/w/Raw_lobster",
      "item_asset_path": "assets/items/raw-lobster.png",
      "section": "Levels 40\u201345",
      "quantity_text": "5\u201310 (noted)",
      "quantity_estimate": 7.5,
      "rarity_fraction": "540/6,400",
      "rarity_percent": "8.44",
      "probability": 0.084375,
      "ge_value": 720,
      "ge_unit_estimate": 96,
      "ha_value": 210,
      "ha_unit_estimate": 28,
      "row_id": "Levels 40\u201345::raw-lobster::540/6,400"
    },
    {
      "item_name": "Raw pike",
      "item_slug": "raw-pike",
      "item_page": "https://oldschool.runescape.wiki/w/Raw_pike",
      "item_asset_path": "assets/items/raw-pike.png",
      "section": "Levels 46\u201349",
      "quantity_text": "30\u201340 (noted)",
      "quantity_estimate": 35.0,
      "rarity_fraction": "900/6,400",
      "rarity_percent": "14.1",
      "probability": 0.140625,
      "ge_value": 4710,
      "ge_unit_estimate": 135,
      "ha_value": 360,
      "ha_unit_estimate": 10,
      "row_id": "Levels 46\u201349::raw-pike::900/6,400"
    },
    {
      "item_name": "Raw salmon",
      "item_slug": "raw-salmon",
      "item_page": "https://oldschool.runescape.wiki/w/Raw_salmon",
      "item_asset_path": "assets/items/raw-salmon.png",
      "section": "Levels 46\u201349",
      "quantity_text": "20\u201330 (noted)",
      "quantity_estimate": 25.0,
      "rarity_fraction": "810/6,400",
      "rarity_percent": "12.7",
      "probability": 0.1265625,
      "ge_value": 900,
      "ge_unit_estimate": 36,
      "ha_value": 360,
      "ha_unit_estimate": 14,
      "row_id": "Levels 46\u201349::raw-salmon::810/6,400"
    },
    {
      "item_name": "Raw tuna",
      "item_slug": "raw-tuna",
      "item_page": "https://oldschool.runescape.wiki/w/Raw_tuna",
      "item_asset_path": "assets/items/raw-tuna.png",
      "section": "Levels 46\u201349",
      "quantity_text": "10\u201320 (noted)",
      "quantity_estimate": 15.0,
      "rarity_fraction": "720/6,400",
      "rarity_percent": "11.3",
      "probability": 0.1125,
      "ge_value": 660,
      "ge_unit_estimate": 44,
      "ha_value": 240,
      "ha_unit_estimate": 16,
      "row_id": "Levels 46\u201349::raw-tuna::720/6,400"
    },
    {
      "item_name": "Raw lobster",
      "item_slug": "raw-lobster",
      "item_page": "https://oldschool.runescape.wiki/w/Raw_lobster",
      "item_asset_path": "assets/items/raw-lobster.png",
      "section": "Levels 46\u201349",
      "quantity_text": "7\u201312 (noted)",
      "quantity_estimate": 9.5,
      "rarity_fraction": "630/6,400",
      "rarity_percent": "9.84",
      "probability": 0.0984375,
      "ge_value": 1008,
      "ge_unit_estimate": 106,
      "ha_value": 294,
      "ha_unit_estimate": 31,
      "row_id": "Levels 46\u201349::raw-lobster::630/6,400"
    },
    {
      "item_name": "Raw bass",
      "item_slug": "raw-bass",
      "item_page": "https://oldschool.runescape.wiki/w/Raw_bass",
      "item_asset_path": "assets/items/raw-bass.png",
      "section": "Levels 46\u201349",
      "quantity_text": "5\u201310 (noted)",
      "quantity_estimate": 7.5,
      "rarity_fraction": "540/6,400",
      "rarity_percent": "8.44",
      "probability": 0.084375,
      "ge_value": 70,
      "ge_unit_estimate": 9,
      "ha_value": 120,
      "ha_unit_estimate": 16,
      "row_id": "Levels 46\u201349::raw-bass::540/6,400"
    },
    {
      "item_name": "Raw salmon",
      "item_slug": "raw-salmon",
      "item_page": "https://oldschool.runescape.wiki/w/Raw_salmon",
      "item_asset_path": "assets/items/raw-salmon.png",
      "section": "Levels 50\u201375",
      "quantity_text": "30\u201340 (noted)",
      "quantity_estimate": 35.0,
      "rarity_fraction": "900/6,400",
      "rarity_percent": "14.1",
      "probability": 0.140625,
      "ge_value": 1350,
      "ge_unit_estimate": 39,
      "ha_value": 540,
      "ha_unit_estimate": 15,
      "row_id": "Levels 50\u201375::raw-salmon::900/6,400"
    },
    {
      "item_name": "Raw tuna",
      "item_slug": "raw-tuna",
      "item_page": "https://oldschool.runescape.wiki/w/Raw_tuna",
      "item_asset_path": "assets/items/raw-tuna.png",
      "section": "Levels 50\u201375",
      "quantity_text": "20\u201330 (noted)",
      "quantity_estimate": 25.0,
      "rarity_fraction": "810/6,400",
      "rarity_percent": "12.7",
      "probability": 0.1265625,
      "ge_value": 1320,
      "ge_unit_estimate": 53,
      "ha_value": 480,
      "ha_unit_estimate": 19,
      "row_id": "Levels 50\u201375::raw-tuna::810/6,400"
    },
    {
      "item_name": "Raw lobster",
      "item_slug": "raw-lobster",
      "item_page": "https://oldschool.runescape.wiki/w/Raw_lobster",
      "item_asset_path": "assets/items/raw-lobster.png",
      "section": "Levels 50\u201375",
      "quantity_text": "10\u201320 (noted)",
      "quantity_estimate": 15.0,
      "rarity_fraction": "720/6,400",
      "rarity_percent": "11.3",
      "probability": 0.1125,
      "ge_value": 1440,
      "ge_unit_estimate": 96,
      "ha_value": 420,
      "ha_unit_estimate": 28,
      "row_id": "Levels 50\u201375::raw-lobster::720/6,400"
    },
    {
      "item_name": "Raw bass",
      "item_slug": "raw-bass",
      "item_page": "https://oldschool.runescape.wiki/w/Raw_bass",
      "item_asset_path": "assets/items/raw-bass.png",
      "section": "Levels 50\u201375",
      "quantity_text": "7\u201312 (noted)",
      "quantity_estimate": 9.5,
      "rarity_fraction": "630/6,400",
      "rarity_percent": "9.84",
      "probability": 0.0984375,
      "ge_value": 98,
      "ge_unit_estimate": 10,
      "ha_value": 168,
      "ha_unit_estimate": 18,
      "row_id": "Levels 50\u201375::raw-bass::630/6,400"
    },
    {
      "item_name": "Raw swordfish",
      "item_slug": "raw-swordfish",
      "item_page": "https://oldschool.runescape.wiki/w/Raw_swordfish",
      "item_asset_path": "assets/items/raw-swordfish.png",
      "section": "Levels 50\u201375",
      "quantity_text": "5\u201310 (noted)",
      "quantity_estimate": 7.5,
      "rarity_fraction": "540/6,400",
      "rarity_percent": "8.44",
      "probability": 0.084375,
      "ge_value": 1010,
      "ge_unit_estimate": 135,
      "ha_value": 240,
      "ha_unit_estimate": 32,
      "row_id": "Levels 50\u201375::raw-swordfish::540/6,400"
    },
    {
      "item_name": "Raw tuna",
      "item_slug": "raw-tuna",
      "item_page": "https://oldschool.runescape.wiki/w/Raw_tuna",
      "item_asset_path": "assets/items/raw-tuna.png",
      "section": "Levels 76\u201378",
      "quantity_text": "30\u201340 (noted)",
      "quantity_estimate": 35.0,
      "rarity_fraction": "900/6,400",
      "rarity_percent": "14.1",
      "probability": 0.140625,
      "ge_value": 1980,
      "ge_unit_estimate": 57,
      "ha_value": 720,
      "ha_unit_estimate": 21,
      "row_id": "Levels 76\u201378::raw-tuna::900/6,400"
    },
    {
      "item_name": "Raw lobster",
      "item_slug": "raw-lobster",
      "item_page": "https://oldschool.runescape.wiki/w/Raw_lobster",
      "item_asset_path": "assets/items/raw-lobster.png",
      "section": "Levels 76\u201378",
      "quantity_text": "20\u201330 (noted)",
      "quantity_estimate": 25.0,
      "rarity_fraction": "810/6,400",
      "rarity_percent": "12.7",
      "probability": 0.1265625,
      "ge_value": 2880,
      "ge_unit_estimate": 115,
      "ha_value": 840,
      "ha_unit_estimate": 34,
      "row_id": "Levels 76\u201378::raw-lobster::810/6,400"
    },
    {
      "item_name": "Raw bass",
      "item_slug": "raw-bass",
      "item_page": "https://oldschool.runescape.wiki/w/Raw_bass",
      "item_asset_path": "assets/items/raw-bass.png",
      "section": "Levels 76\u201378",
      "quantity_text": "10\u201320 (noted)",
      "quantity_estimate": 15.0,
      "rarity_fraction": "720/6,400",
      "rarity_percent": "11.3",
      "probability": 0.1125,
      "ge_value": 140,
      "ge_unit_estimate": 9,
      "ha_value": 240,
      "ha_unit_estimate": 16,
      "row_id": "Levels 76\u201378::raw-bass::720/6,400"
    },
    {
      "item_name": "Raw swordfish",
      "item_slug": "raw-swordfish",
      "item_page": "https://oldschool.runescape.wiki/w/Raw_swordfish",
      "item_asset_path": "assets/items/raw-swordfish.png",
      "section": "Levels 76\u201378",
      "quantity_text": "7\u201312 (noted)",
      "quantity_estimate": 9.5,
      "rarity_fraction": "630/6,400",
      "rarity_percent": "9.84",
      "probability": 0.0984375,
      "ge_value": 1414,
      "ge_unit_estimate": 149,
      "ha_value": 336,
      "ha_unit_estimate": 35,
      "row_id": "Levels 76\u201378::raw-swordfish::630/6,400"
    },
    {
      "item_name": "Raw shark",
      "item_slug": "raw-shark",
      "item_page": "https://oldschool.runescape.wiki/w/Raw_shark",
      "item_asset_path": "assets/items/raw-shark.png",
      "section": "Levels 76\u201378",
      "quantity_text": "5\u201310 (noted)",
      "quantity_estimate": 7.5,
      "rarity_fraction": "540/6,400",
      "rarity_percent": "8.44",
      "probability": 0.084375,
      "ge_value": 3530,
      "ge_unit_estimate": 471,
      "ha_value": 510,
      "ha_unit_estimate": 68,
      "row_id": "Levels 76\u201378::raw-shark::540/6,400"
    },
    {
      "item_name": "Raw lobster",
      "item_slug": "raw-lobster",
      "item_page": "https://oldschool.runescape.wiki/w/Raw_lobster",
      "item_asset_path": "assets/items/raw-lobster.png",
      "section": "Levels 79\u201380",
      "quantity_text": "30\u201340 (noted)",
      "quantity_estimate": 35.0,
      "rarity_fraction": "900/6,400",
      "rarity_percent": "14.1",
      "probability": 0.140625,
      "ge_value": 4320,
      "ge_unit_estimate": 123,
      "ha_value": 1260,
      "ha_unit_estimate": 36,
      "row_id": "Levels 79\u201380::raw-lobster::900/6,400"
    },
    {
      "item_name": "Raw bass",
      "item_slug": "raw-bass",
      "item_page": "https://oldschool.runescape.wiki/w/Raw_bass",
      "item_asset_path": "assets/items/raw-bass.png",
      "section": "Levels 79\u201380",
      "quantity_text": "20\u201330 (noted)",
      "quantity_estimate": 25.0,
      "rarity_fraction": "810/6,400",
      "rarity_percent": "12.7",
      "probability": 0.1265625,
      "ge_value": 280,
      "ge_unit_estimate": 11,
      "ha_value": 480,
      "ha_unit_estimate": 19,
      "row_id": "Levels 79\u201380::raw-bass::810/6,400"
    },
    {
      "item_name": "Raw swordfish",
      "item_slug": "raw-swordfish",
      "item_page": "https://oldschool.runescape.wiki/w/Raw_swordfish",
      "item_asset_path": "assets/items/raw-swordfish.png",
      "section": "Levels 79\u201380",
      "quantity_text": "10\u201320 (noted)",
      "quantity_estimate": 15.0,
      "rarity_fraction": "720/6,400",
      "rarity_percent": "11.3",
      "probability": 0.1125,
      "ge_value": 2020,
      "ge_unit_estimate": 135,
      "ha_value": 480,
      "ha_unit_estimate": 32,
      "row_id": "Levels 79\u201380::raw-swordfish::720/6,400"
    },
    {
      "item_name": "Raw shark",
      "item_slug": "raw-shark",
      "item_page": "https://oldschool.runescape.wiki/w/Raw_shark",
      "item_asset_path": "assets/items/raw-shark.png",
      "section": "Levels 79\u201380",
      "quantity_text": "7\u201312 (noted)",
      "quantity_estimate": 9.5,
      "rarity_fraction": "630/6,400",
      "rarity_percent": "9.84",
      "probability": 0.0984375,
      "ge_value": 4942,
      "ge_unit_estimate": 520,
      "ha_value": 714,
      "ha_unit_estimate": 75,
      "row_id": "Levels 79\u201380::raw-shark::630/6,400"
    },
    {
      "item_name": "Raw sea turtle",
      "item_slug": "raw-sea-turtle",
      "item_page": "https://oldschool.runescape.wiki/w/Raw_sea_turtle",
      "item_asset_path": "assets/items/raw-sea-turtle.png",
      "section": "Levels 79\u201380",
      "quantity_text": "5\u201310 (noted)",
      "quantity_estimate": 7.5,
      "rarity_fraction": "540/6,400",
      "rarity_percent": "8.44",
      "probability": 0.084375,
      "ge_value": 3385,
      "ge_unit_estimate": 451,
      "ha_value": 600,
      "ha_unit_estimate": 80,
      "row_id": "Levels 79\u201380::raw-sea-turtle::540/6,400"
    },
    {
      "item_name": "Raw bass",
      "item_slug": "raw-bass",
      "item_page": "https://oldschool.runescape.wiki/w/Raw_bass",
      "item_asset_path": "assets/items/raw-bass.png",
      "section": "Levels 81+",
      "quantity_text": "30\u201340 (noted)",
      "quantity_estimate": 35.0,
      "rarity_fraction": "900/6,400",
      "rarity_percent": "14.1",
      "probability": 0.140625,
      "ge_value": 420,
      "ge_unit_estimate": 12,
      "ha_value": 720,
      "ha_unit_estimate": 21,
      "row_id": "Levels 81+::raw-bass::900/6,400"
    },
    {
      "item_name": "Raw swordfish",
      "item_slug": "raw-swordfish",
      "item_page": "https://oldschool.runescape.wiki/w/Raw_swordfish",
      "item_asset_path": "assets/items/raw-swordfish.png",
      "section": "Levels 81+",
      "quantity_text": "20\u201330 (noted)",
      "quantity_estimate": 25.0,
      "rarity_fraction": "810/6,400",
      "rarity_percent": "12.7",
      "probability": 0.1265625,
      "ge_value": 4040,
      "ge_unit_estimate": 162,
      "ha_value": 960,
      "ha_unit_estimate": 38,
      "row_id": "Levels 81+::raw-swordfish::810/6,400"
    },
    {
      "item_name": "Raw shark",
      "item_slug": "raw-shark",
      "item_page": "https://oldschool.runescape.wiki/w/Raw_shark",
      "item_asset_path": "assets/items/raw-shark.png",
      "section": "Levels 81+",
      "quantity_text": "10\u201320 (noted)",
      "quantity_estimate": 15.0,
      "rarity_fraction": "720/6,400",
      "rarity_percent": "11.3",
      "probability": 0.1125,
      "ge_value": 7060,
      "ge_unit_estimate": 471,
      "ha_value": 1020,
      "ha_unit_estimate": 68,
      "row_id": "Levels 81+::raw-shark::720/6,400"
    },
    {
      "item_name": "Raw sea turtle",
      "item_slug": "raw-sea-turtle",
      "item_page": "https://oldschool.runescape.wiki/w/Raw_sea_turtle",
      "item_asset_path": "assets/items/raw-sea-turtle.png",
      "section": "Levels 81+",
      "quantity_text": "7\u201312 (noted)",
      "quantity_estimate": 9.5,
      "rarity_fraction": "630/6,400",
      "rarity_percent": "9.84",
      "probability": 0.0984375,
      "ge_value": 4739,
      "ge_unit_estimate": 499,
      "ha_value": 840,
      "ha_unit_estimate": 88,
      "row_id": "Levels 81+::raw-sea-turtle::630/6,400"
    },
    {
      "item_name": "Raw manta ray",
      "item_slug": "raw-manta-ray",
      "item_page": "https://oldschool.runescape.wiki/w/Raw_manta_ray",
      "item_asset_path": "assets/items/raw-manta-ray.png",
      "section": "Levels 81+",
      "quantity_text": "5\u201310 (noted)",
      "quantity_estimate": 7.5,
      "rarity_fraction": "540/6,400",
      "rarity_percent": "8.44",
      "probability": 0.084375,
      "ge_value": 6300,
      "ge_unit_estimate": 840,
      "ha_value": 600,
      "ha_unit_estimate": 80,
      "row_id": "Levels 81+::raw-manta-ray::540/6,400"
    },
    {
      "item_name": "Plank",
      "item_slug": "plank",
      "item_page": "https://oldschool.runescape.wiki/w/Plank",
      "item_asset_path": "assets/items/plank.png",
      "section": "Other",
      "quantity_text": "20\u201330 (noted)",
      "quantity_estimate": 25.0,
      "rarity_fraction": "7/160",
      "rarity_percent": "4.38",
      "probability": 0.04375,
      "ge_value": 3040,
      "ge_unit_estimate": 122,
      "ha_value": 0,
      "ha_unit_estimate": null,
      "row_id": "Other::plank::7/160"
    },
    {
      "item_name": "Oak plank",
      "item_slug": "oak-plank",
      "item_page": "https://oldschool.runescape.wiki/w/Oak_plank",
      "item_asset_path": "assets/items/oak-plank.png",
      "section": "Other",
      "quantity_text": "15\u201325 (noted)",
      "quantity_estimate": 20.0,
      "rarity_fraction": "1/32",
      "rarity_percent": "3.13",
      "probability": 0.03125,
      "ge_value": 8250,
      "ge_unit_estimate": 412,
      "ha_value": 2250,
      "ha_unit_estimate": 112,
      "row_id": "Other::oak-plank::1/32"
    },
    {
      "item_name": "Seaweed",
      "item_slug": "seaweed",
      "item_page": "https://oldschool.runescape.wiki/w/Seaweed",
      "item_asset_path": "assets/items/seaweed.png",
      "section": "Other",
      "quantity_text": "20\u201360 (noted)",
      "quantity_estimate": 40.0,
      "rarity_fraction": "1/40",
      "rarity_percent": "2.5",
      "probability": 0.025,
      "ge_value": 140,
      "ge_unit_estimate": 4,
      "ha_value": 20,
      "ha_unit_estimate": 0,
      "row_id": "Other::seaweed::1/40"
    },
    {
      "item_name": "Steel nails",
      "item_slug": "steel-nails",
      "item_page": "https://oldschool.runescape.wiki/w/Steel_nails",
      "item_asset_path": "assets/items/steel-nails.png",
      "section": "Other",
      "quantity_text": "300\u2013500",
      "quantity_estimate": 400.0,
      "rarity_fraction": "1/80",
      "rarity_percent": "1.25",
      "probability": 0.0125,
      "ge_value": 7800,
      "ge_unit_estimate": 20,
      "ha_value": 300,
      "ha_unit_estimate": 1,
      "row_id": "Other::steel-nails::1/80"
    },
    {
      "item_name": "Feather",
      "item_slug": "feather",
      "item_page": "https://oldschool.runescape.wiki/w/Feather",
      "item_asset_path": "assets/items/feather.png",
      "section": "Other",
      "quantity_text": "800\u20131,600",
      "quantity_estimate": 1200.0,
      "rarity_fraction": "1/80",
      "rarity_percent": "1.25",
      "probability": 0.0125,
      "ge_value": 2400,
      "ge_unit_estimate": 2,
      "ha_value": 800,
      "ha_unit_estimate": 1,
      "row_id": "Other::feather::1/80"
    },
    {
      "item_name": "Fishing bait",
      "item_slug": "fishing-bait",
      "item_page": "https://oldschool.runescape.wiki/w/Fishing_bait",
      "item_asset_path": "assets/items/fishing-bait.png",
      "section": "Other",
      "quantity_text": "800\u20131,600",
      "quantity_estimate": 1200.0,
      "rarity_fraction": "1/80",
      "rarity_percent": "1.25",
      "probability": 0.0125,
      "ge_value": 3200,
      "ge_unit_estimate": 3,
      "ha_value": 800,
      "ha_unit_estimate": 1,
      "row_id": "Other::fishing-bait::1/80"
    }
  ],
  "variants": [],
  "sections": [
    {
      "name": "Levels 35\u201339",
      "row_count": 5,
      "total_probability": 0.5625
    },
    {
      "name": "Levels 40\u201345",
      "row_count": 5,
      "total_probability": 0.5625
    },
    {
      "name": "Levels 46\u201349",
      "row_count": 5,
      "total_probability": 0.5625
    },
    {
      "name": "Levels 50\u201375",
      "row_count": 5,
      "total_probability": 0.5625
    },
    {
      "name": "Levels 76\u201378",
      "row_count": 5,
      "total_probability": 0.5625
    },
    {
      "name": "Levels 79\u201380",
      "row_count": 5,
      "total_probability": 0.5625
    },
    {
      "name": "Levels 81+",
      "row_count": 5,
      "total_probability": 0.5625
    },
    {
      "name": "Other",
      "row_count": 6,
      "total_probability": 0.1375
    },
    {
      "name": "Unique",
      "row_count": 10,
      "total_probability": 0.327625
    }
  ],
  "simulation": {
    "guaranteed_row_ids": [],
    "independent_sections": [],
    "exclusive_sections": [
      {
        "label": "Main pool",
        "row_ids": [
          "Unique::spirit-flakes::1/4",
          "Unique::casket-reward-pool::1/20",
          "Unique::soaked-page::149/8,000",
          "Unique::fish-barrel::1/400",
          "Unique::soaked-page::1/400",
          "Unique::tackle-box::1/400",
          "Unique::big-harpoonfish::1/1,600",
          "Unique::tome-of-water-empty::1/1,600",
          "Unique::tiny-tempor::1/8,000",
          "Unique::dragon-harpoon::1/8,000",
          "Levels 35\u201339::raw-herring::900/6,400",
          "Levels 35\u201339::raw-mackerel::810/6,400",
          "Levels 35\u201339::raw-pike::720/6,400",
          "Levels 35\u201339::raw-salmon::630/6,400",
          "Levels 35\u201339::raw-tuna::540/6,400",
          "Levels 40\u201345::raw-mackerel::900/6,400",
          "Levels 40\u201345::raw-pike::810/6,400",
          "Levels 40\u201345::raw-salmon::720/6,400",
          "Levels 40\u201345::raw-tuna::630/6,400",
          "Levels 40\u201345::raw-lobster::540/6,400",
          "Levels 46\u201349::raw-pike::900/6,400",
          "Levels 46\u201349::raw-salmon::810/6,400",
          "Levels 46\u201349::raw-tuna::720/6,400",
          "Levels 46\u201349::raw-lobster::630/6,400",
          "Levels 46\u201349::raw-bass::540/6,400",
          "Levels 50\u201375::raw-salmon::900/6,400",
          "Levels 50\u201375::raw-tuna::810/6,400",
          "Levels 50\u201375::raw-lobster::720/6,400",
          "Levels 50\u201375::raw-bass::630/6,400",
          "Levels 50\u201375::raw-swordfish::540/6,400",
          "Levels 76\u201378::raw-tuna::900/6,400",
          "Levels 76\u201378::raw-lobster::810/6,400",
          "Levels 76\u201378::raw-bass::720/6,400",
          "Levels 76\u201378::raw-swordfish::630/6,400",
          "Levels 76\u201378::raw-shark::540/6,400",
          "Levels 79\u201380::raw-lobster::900/6,400",
          "Levels 79\u201380::raw-bass::810/6,400",
          "Levels 79\u201380::raw-swordfish::720/6,400",
          "Levels 79\u201380::raw-shark::630/6,400",
          "Levels 79\u201380::raw-sea-turtle::540/6,400",
          "Levels 81+::raw-bass::900/6,400",
          "Levels 81+::raw-swordfish::810/6,400",
          "Levels 81+::raw-shark::720/6,400",
          "Levels 81+::raw-sea-turtle::630/6,400",
          "Levels 81+::raw-manta-ray::540/6,400",
          "Other::plank::7/160",
          "Other::oak-plank::1/32",
          "Other::seaweed::1/40",
          "Other::steel-nails::1/80",
          "Other::feather::1/80",
          "Other::fishing-bait::1/80"
        ],
        "total_probability": null
      }
    ],
    "note": "Simulation uses wiki-listed per-row rarities. Activities with custom multi-roll reward systems remain approximations."
  },
  "fetched_at": "2026-03-19T04:44:27.262587+00:00"
}
